shapwaterfall/__init__.py
shapwaterfall/shapwaterfall.py
shapwaterfall-0.3.1.dist-info/METADATA
shapwaterfall-0.3.1.dist-info/WHEEL
shapwaterfall-0.3.1.dist-info/top_level.txt
shapwaterfall-0.3.1.dist-info/RECORD
