Metadata-Version: 2.1
Name: shapwaterfall
Version: 0.3.1
Summary: A SHAP Waterfall Chart for interpreting local differences between observations
Home-page: https://github.com/JohnBHalstead/shapwaterfall
Author: John Halstead
Author-email: jhalstead@vmware.com
License: UNKNOWN
Platform: UNKNOWN
Classifier: Development Status :: 4 - Beta
Classifier: Programming Language :: Python :: 3
Classifier: License :: OSI Approved :: MIT License
Classifier: Operating System :: OS Independent
Requires-Python: >=3.6
Requires-Dist: shap
Requires-Dist: waterfallcharts
Requires-Dist: numpy
Requires-Dist: matplotlib
Requires-Dist: pandas
